{
  "he": {
    "main": {
      "connection": [
        "올해는 사람과의 연결이 실제 기회로 이어질 가능성이 큽니다. 혼자 밀어붙이기보다 협력과 조율을 잘 활용하는 편이 더 큰 결과를 만들 수 있습니다.",
        "좋은 반응, 좋은 파트너, 좋은 타이밍이 자연스럽게 이어질 수 있는 해입니다. 관계를 닫아두기보다 열어두는 편이 유리할 수 있습니다.",
        "올해는 사람을 통해 막혀 있던 흐름이 다시 열릴 수 있습니다. 필요한 순간에 적절한 도움을 받게 될 가능성도 있습니다.",
        "혼자 해결하려던 문제도 누군가와 맞추는 과정에서 더 좋은 답이 보일 수 있습니다."
      ],
      "expansion": [
        "올해는 연결이 확장으로 이어질 가능성이 있습니다. 좋은 관계가 일과 돈, 기회의 범위를 넓히는 흐름으로 작용할 수 있습니다.",
        "내가 가진 것을 밖으로 연결할수록 기회가 커질 수 있습니다. 다만 모든 흐름을 다 잡기보다 맞는 연결을 고르는 태도가 중요합니다.",
        "관계를 통해 활동 범위가 넓어질 가능성이 있습니다. 소개, 제안, 피드백이 다음 단계로 이어질 수 있습니다.",
        "올해는 사람이 곧 기회가 될 수 있는 흐름이라, 반응을 너무 늦추지 않는 편이 좋습니다."
      ],
      "harvest": [
        "그동안 쌓아온 관계가 실제 도움이나 결과로 돌아올 가능성이 있습니다.",
        "조용히 이어오던 연결이 올해는 의미 있는 결실로 보일 수 있습니다.",
        "관계에서의 신뢰가 말이 아니라 실제 기회, 실제 성과로 이어질 수 있습니다.",
        "오래 본 사람과의 연결이 생각보다 큰 힘이 되어줄 수 있는 해입니다."
      ],
      "foundation": [
        "좋은 관계가 기반이 되는 해가 될 수 있습니다. 사람운이 편인 쪽으로 흐를 가능성이 있습니다.",
        "올해는 혼자 버티는 구조보다 연결을 포함한 구조가 더 안정적으로 작동할 수 있습니다.",
        "관계의 질이 전체 흐름의 안정감을 키우는 역할을 할 수 있습니다.",
        "신뢰할 수 있는 인연을 잘 챙기는 것만으로도 해 전체 흐름이 훨씬 편해질 수 있습니다."
      ]
    },
    "love": {
      "connection": [
        "애정운은 사람을 통해 기회가 이어지기 쉬운 흐름입니다. 소개, 재연결, 자연스러운 만남 안에서 좋은 인연이 들어올 가능성이 있습니다.",
        "싱글이라면 관계의 시작점이 생각보다 가볍고 자연스러울 수 있습니다. 억지로 만들기보다 이어지는 흐름을 잘 보는 편이 좋습니다.",
        "커플이라면 둘 사이를 부드럽게 이어주는 환경과 타이밍의 도움을 받을 수 있습니다.",
        "관계를 편하게 여는 태도가 애정운을 더 좋게 만들 가능성이 큽니다."
      ],
      "harvest": [
        "애정운은 오래 이어온 관계에서 결과가 보일 수 있는 흐름입니다.",
        "애매했던 관계가 조금 더 분명해지거나, 편안한 방향으로 정리될 가능성이 있습니다.",
        "커플이라면 함께 쌓아온 신뢰가 실제 안정감으로 느껴질 수 있습니다.",
        "사랑은 크게 흔들리기보다 자연스럽게 방향이 잡힐 수 있는 해입니다."
      ],
      "foundation": [
        "애정운은 감정의 크기보다 신뢰와 일관성이 중요하게 작용할 수 있습니다.",
        "관계를 무리하게 흔들지 않는 태도가 오히려 더 큰 안정으로 이어질 수 있습니다.",
        "싱글이라면 나와 잘 맞는 사람을 알아보는 감각이 좋아질 수 있습니다.",
        "커플이라면 생활 리듬과 반응 방식이 잘 맞을수록 관계운이 더 편안해질 수 있습니다."
      ]
    },
    "money": {
      "connection": [
        "재물운은 사람과 정보 연결을 잘 활용할수록 좋아질 가능성이 있습니다.",
        "좋은 조건, 좋은 정보, 좋은 비교 지점이 자연스럽게 들어올 수 있습니다.",
        "혼자 감으로 판단하기보다 문의, 조언, 비교를 거칠수록 더 실속 있는 선택이 가능할 수 있습니다.",
        "금전 문제에서도 관계와 정보 흐름이 직접적인 도움이 될 가능성이 있습니다."
      ],
      "expansion": [
        "재물운은 연결을 통해 범위가 넓어질 가능성이 있습니다. 다만 확장 자체보다 구조를 함께 챙기는 편이 좋습니다.",
        "수익 기회가 늘 수 있지만 그만큼 움직이는 돈도 많아질 수 있습니다.",
        "사람을 통해 기회가 들어올 수 있으니, 조건과 책임 범위를 함께 확인하는 편이 좋습니다.",
        "돈은 흐를 수 있지만 기준 없이 넓히면 부담도 함께 커질 수 있습니다."
      ],
      "harvest": [
        "그동안의 관리와 선택이 관계를 통해 실제 이득으로 이어질 수 있습니다.",
        "주변과 연결된 정보나 기회가 실질적인 재정 안정으로 이어질 가능성이 있습니다.",
        "작게 쌓인 실속이 올해는 더 분명하게 체감될 수 있습니다.",
        "돈 문제는 혼자 닫아두기보다 잘 연결할수록 결과가 좋아질 수 있습니다."
      ]
    },
    "work": {
      "connection": [
        "일운은 협력과 연결이 실제 성과로 이어질 가능성이 큽니다.",
        "혼자 끌고 가기보다 팀, 파트너, 피드백 흐름을 잘 활용할수록 더 편하게 갈 수 있습니다.",
        "업무상 좋은 연결과 소개가 다음 기회로 이어질 수 있습니다.",
        "내 실력과 외부 반응이 잘 맞아떨어지는 장면이 생길 가능성이 있습니다."
      ],
      "expansion": [
        "일운은 사람을 통해 판이 넓어질 가능성이 있습니다. 역할이 커지거나 연결되는 영역이 늘어날 수 있습니다.",
        "좋은 협업이 새로운 책임이나 새로운 기회로 이어질 수 있습니다.",
        "관계가 넓어질수록 가능성도 늘지만, 감당 범위를 같이 챙기는 편이 좋습니다.",
        "업무는 혼자 잘하는 것보다 함께 잘 움직이는 쪽이 더 강하게 작용할 수 있습니다."
      ],
      "harvest": [
        "그동안 쌓아온 신뢰가 실제 평가와 성과로 이어질 가능성이 있습니다.",
        "좋은 관계가 좋은 결과를 만들 수 있는 해입니다.",
        "협업에서 쌓인 평판이 기회와 성과로 돌아올 수 있습니다.",
        "오래 이어온 업무 인연이 올해는 특히 힘이 되어줄 가능성이 있습니다."
      ]
    },
    "relationship": {
      "connection": [
        "대인운은 사람을 통해 길이 열리는 흐름에 가깝습니다.",
        "필요한 순간에 적절한 사람을 만나거나, 좋은 반응을 얻을 가능성이 있습니다.",
        "관계는 넓이보다 질이 중요하지만, 닫혀 있기보다 열어두는 편이 더 유리할 수 있습니다.",
        "올해는 사람과 사람을 잇는 역할이 자연스럽게 맞을 수 있습니다."
      ],
      "foundation": [
        "신뢰할 수 있는 사람들과의 연결이 내 생활 전반을 안정시키는 역할을 할 수 있습니다.",
        "올해는 믿을 수 있는 관계를 잘 유지하는 것만으로도 큰 힘이 될 수 있습니다.",
        "좋은 사람을 많이 두는 것보다 좋은 연결을 오래 가져가는 편이 중요할 수 있습니다.",
        "관계는 조용하지만 든든하게 작동할 가능성이 있습니다."
      ],
      "harvest": [
        "오래 쌓아온 관계가 실제 도움이나 위로로 돌아올 수 있습니다.",
        "애매했던 인연보다 남을 관계가 더 또렷해질 가능성이 있습니다.",
        "좋은 사람은 더 가까워지고, 피로한 관계는 자연스럽게 멀어질 수 있습니다.",
        "대인운은 조용한 결실을 보여줄 가능성이 있습니다."
      ]
    },
    "advice": {
      "connection": [
        "올해는 좋은 연결을 피하지 말고 활용해보세요.",
        "혼자 다 하려 하기보다 사람의 흐름을 잘 쓰는 편이 좋습니다.",
        "도움이 들어올 때 괜히 버티지 않는 편이 더 유리할 수 있습니다.",
        "좋은 사람과 좋은 타이밍을 가볍게 넘기지 마세요."
      ]
    }
  },
  "chong": {
    "main": {
      "caution": [
        "올해는 흐름이 부딪히는 장면이 종종 생길 수 있어 조정과 방어가 중요할 수 있습니다.",
        "무리하게 확장하거나 빨리 결론내리면 다시 손볼 일이 생길 가능성이 있습니다.",
        "사람, 일정, 역할이 엇갈릴 수 있어 확인과 정리가 특히 중요합니다.",
        "해 전체가 나쁘다기보다, 무리한 밀어붙임이 부담으로 돌아오기 쉬운 흐름일 수 있습니다."
      ],
      "adjustment": [
        "올해는 바꾸지 않고 버티는 것보다 조정하고 정리하는 태도가 더 현실적일 수 있습니다.",
        "답답하게 느껴지는 흐름이 있다면 억지로 밀기보다 구조를 손보는 편이 낫습니다.",
        "일, 돈, 관계 모두에서 너무 벌어진 부분을 정리하는 과정이 중요할 수 있습니다.",
        "불편한 장면이 생기더라도 그것이 방향 조정 신호일 가능성이 큽니다."
      ],
      "foundation": [
        "올해는 흔들리지 않는 기준을 먼저 세우는 것이 가장 중요할 수 있습니다.",
        "크게 얻는 것보다 크게 무너지지 않는 구조를 만드는 편이 더 강한 선택이 될 수 있습니다.",
        "지금 필요한 것은 속도보다 안정과 감당 범위 조정일 수 있습니다.",
        "버티기만 하려 하기보다 생활과 일의 기반을 다시 잡는 편이 좋습니다."
      ],
      "harvest": [
        "무리한 욕심을 줄이고 정리할 것을 정리하면 오히려 해 후반에 결과가 더 선명해질 수 있습니다.",
        "충 흐름 속에서도 구조를 바로잡은 사람에게는 정리된 결실이 남을 수 있습니다.",
        "처음부터 큰 수확보다 조정 끝에 남는 결과를 챙기는 편이 좋습니다.",
        "올해는 '덜 틀리게 가는 것'이 결국 좋은 결과를 만들 수 있습니다."
      ]
    },
    "love": {
      "caution": [
        "애정운은 감정 반응이 커지기 쉬워 관계 피로를 조심해야 할 수 있습니다.",
        "답을 빨리 확인하려 하거나, 감정을 바로 표현하면 오히려 엇갈림이 커질 수 있습니다.",
        "싱글이라면 끌림보다 안정감을 먼저 보는 편이 좋습니다.",
        "커플이라면 사소한 말투와 타이밍이 관계 분위기에 크게 작용할 수 있습니다."
      ],
      "adjustment": [
        "관계 안에서 기대치와 거리감을 다시 맞추는 과정이 중요할 수 있습니다.",
        "무작정 끌고 가기보다 불편한 지점을 정리하는 편이 오히려 관계를 지킬 수 있습니다.",
        "감정을 설명하기보다 먼저 가라앉히는 태도가 도움이 될 수 있습니다.",
        "애정운은 강하게 밀기보다 조정과 회복 쪽에 의미가 있을 수 있습니다."
      ],
      "foundation": [
        "관계를 덜 지치게 만드는 운영이 중요할 수 있습니다.",
        "사랑을 키우기보다 상처를 키우지 않는 태도가 더 중요하게 작용할 수 있습니다.",
        "싱글이라면 나에게 맞는 관계 기준을 다시 세우는 해가 될 수 있습니다.",
        "커플이라면 편안함과 생활 균형을 먼저 챙기는 편이 좋습니다."
      ]
    },
    "money": {
      "caution": [
        "재물운은 급한 판단과 과한 낙관을 특히 조심해야 할 수 있습니다.",
        "좋아 보여도 조건, 기간, 유지비를 다시 확인하는 편이 좋습니다.",
        "반복 지출이나 작은 누수가 더 크게 느껴질 수 있어 점검이 중요합니다.",
        "무리하게 벌이기보다 손실을 줄이는 운영이 더 잘 맞을 수 있습니다."
      ],
      "adjustment": [
        "재정 구조를 정리하고 소비 기준을 다시 맞추는 일이 필요할 수 있습니다.",
        "기존 지출 습관이나 애매한 비용 구조를 손보면 체감이 달라질 수 있습니다.",
        "돈 문제는 공격보다 조정과 정비에서 답이 나올 가능성이 큽니다.",
        "정리해야 할 재정 문제가 보이면 미루지 않는 편이 좋습니다."
      ],
      "foundation": [
        "재물운은 크게 벌기보다 버틸 수 있는 구조를 만드는 편이 더 중요할 수 있습니다.",
        "무리한 투자보다 생활 안정과 현금 흐름 관리가 우선일 수 있습니다.",
        "올해는 기준을 단단히 잡아야 흔들림을 줄일 수 있습니다.",
        "기본적인 관리가 곧 가장 큰 보호가 될 수 있습니다."
      ]
    },
    "work": {
      "caution": [
        "일운은 일정 엇갈림, 역할 충돌, 전달 오류를 특히 조심해야 할 수 있습니다.",
        "빠르게 끝내려다 다시 손볼 일이 생길 가능성이 있어 확인이 중요합니다.",
        "업무상 피로와 압박이 함께 올라올 수 있어 경계 설정이 필요할 수 있습니다.",
        "과한 자신감보다 체크리스트가 더 도움이 되는 해일 수 있습니다."
      ],
      "adjustment": [
        "업무 구조, 역할 분담, 우선순위를 다시 맞추는 과정이 중요할 수 있습니다.",
        "새 일을 늘리기보다 현재 일을 더 맞게 정리하는 편이 좋습니다.",
        "복잡한 일을 단순화하는 능력이 해 전체를 훨씬 편하게 만들 수 있습니다.",
        "일은 많이 하는 것보다 실수 가능성을 줄이는 쪽이 더 중요할 수 있습니다."
      ],
      "foundation": [
        "일운은 기반을 다시 다지는 태도가 중요할 수 있습니다.",
        "무너지지 않는 구조를 만드는 것이 성과보다 우선일 수 있습니다.",
        "업무상 흔들릴수록 기준, 기록, 루틴을 단단히 가져가는 편이 좋습니다.",
        "해 전체로 보면 속도보다 지속 가능성이 더 중요할 수 있습니다."
      ]
    },
    "relationship": {
      "caution": [
        "대인운은 사람 때문에 피로가 커질 수 있어 거리 조절이 중요할 수 있습니다.",
        "모든 기대와 부탁을 다 받아내려 하면 부담이 빠르게 커질 수 있습니다.",
        "관계가 나쁘다기보다 엇갈림과 감정 소모를 줄이는 운영이 더 중요할 수 있습니다.",
        "말실수나 타이밍 미스가 길게 남지 않도록 표현을 다듬는 편이 좋습니다."
      ],
      "adjustment": [
        "올해는 넓히기보다 정리와 선 긋기가 더 중요할 수 있습니다.",
        "좋은 관계를 남기기 위해 불필요한 감정 소모를 줄이는 태도가 필요할 수 있습니다.",
        "가까운 관계일수록 반응 속도를 늦추는 편이 좋습니다.",
        "사람과의 거리감을 건강하게 다시 맞추는 해가 될 수 있습니다."
      ],
      "foundation": [
        "대인운은 많이 만나기보다 편하게 갈 수 있는 관계를 남기는 편이 좋습니다.",
        "내 리듬을 먼저 지켜야 관계도 덜 흔들릴 수 있습니다.",
        "해 전체로 보면 양보다 질, 넓이보다 기준이 중요할 수 있습니다.",
        "사람을 잘 고르는 태도가 해 전체 흐름을 지켜줄 수 있습니다."
      ]
    },
    "advice": {
      "caution": [
        "올해는 맞서기보다 조정하는 태도가 더 큰 손실을 막아줄 수 있습니다.",
        "서두를수록 엇갈릴 가능성이 커지니 기준과 확인을 먼저 챙기세요.",
        "무리한 확장보다 실수와 피로를 줄이는 데 집중하는 편이 좋습니다.",
        "빠른 답보다 오래 버틸 수 있는 답을 고르는 편이 유리할 수 있습니다."
      ]
    }
  },
  "normal": {
    "main": {
      "foundation": [
        "올해는 큰 충돌보다 안정적인 운영과 기본 관리가 더 중요할 수 있습니다.",
        "과하게 흔들기보다 현재 흐름을 잘 유지하는 태도가 더 좋은 결과를 만들 가능성이 있습니다.",
        "특별히 큰 파도보다 작은 선택 차이가 누적되어 결과를 만드는 해가 될 수 있습니다.",
        "무리하지 않으면 비교적 편안하게 갈 수 있는 흐름일 가능성이 큽니다."
      ],
      "adjustment": [
        "올해는 아주 크게 바꾸기보다 필요한 부분만 손보는 식의 조정이 잘 맞을 수 있습니다.",
        "기본은 안정적이지만 작은 태도 차이가 체감 차이를 만들 수 있습니다.",
        "흐름은 무난해 보여도 관리와 점검을 소홀히 하면 금방 번거로움이 생길 수 있습니다.",
        "크게 흔들기보다 조금씩 맞추는 편이 더 현실적일 수 있습니다."
      ],
      "harvest": [
        "올해는 작은 결과가 반복되면서 체감이 좋아질 가능성이 있습니다.",
        "거창한 한 번보다 조용한 누적이 더 강하게 작용할 수 있습니다.",
        "기본을 잘 지키는 사람일수록 해 후반에 성과가 더 분명해질 수 있습니다.",
        "크지 않아 보여도 꾸준한 진전이 의미 있게 쌓일 수 있습니다."
      ],
      "connection": [
        "대체로 무난한 흐름 속에서도 사람과 연결되는 장면은 꾸준히 이어질 가능성이 있습니다.",
        "관계는 넓히기보다 안정적으로 유지하는 태도가 더 잘 맞을 수 있습니다.",
        "좋은 연결이 아주 강하게 밀려오진 않아도 필요한 순간에 충분히 도움이 될 가능성이 있습니다.",
        "무난한 해일수록 사람과의 기본 예의와 일관성이 더 큰 힘이 될 수 있습니다."
      ]
    },
    "love": {
      "foundation": [
        "애정운은 강한 자극보다 안정적인 관계 유지 쪽에 더 무게가 실릴 수 있습니다.",
        "싱글이라면 나와 잘 맞는 사람을 차분히 보는 해가 될 수 있습니다.",
        "커플이라면 특별한 이벤트보다 일상적 편안함과 일관성이 더 중요할 수 있습니다.",
        "올해는 관계를 크게 흔들기보다 편안하게 이어가는 쪽이 더 좋을 수 있습니다."
      ],
      "adjustment": [
        "애정운은 큰 갈등보다 작은 오해와 거리감 조정이 중요할 수 있습니다.",
        "관계를 무겁게 끌기보다 리듬을 맞추는 과정이 더 도움이 될 수 있습니다.",
        "싱글이라면 감정보다 기준을 다듬는 시간이 될 수 있습니다.",
        "커플이라면 표현의 방식과 타이밍을 조금만 조정해도 분위기가 달라질 수 있습니다."
      ],
      "harvest": [
        "애정운은 조용하지만 안정적인 결과를 보여줄 수 있습니다.",
        "오래 보던 관계의 의미가 조금 더 분명해질 가능성이 있습니다.",
        "크게 드러나지 않아도 관계 안의 신뢰가 쌓여갈 수 있습니다.",
        "올해는 편안함 자체가 관계의 좋은 결과로 느껴질 수 있습니다."
      ]
    },
    "money": {
      "foundation": [
        "재물운은 큰 변화보다 안정적 관리와 구조 유지가 중요할 수 있습니다.",
        "돈 문제는 익숙한 기준을 잘 지키는 편이 더 유리할 가능성이 있습니다.",
        "무리한 확장보다 생활 흐름과 현금 리듬을 안정시키는 편이 좋습니다.",
        "기본적인 지출 관리만 잘해도 해 전체가 훨씬 편안해질 수 있습니다."
      ],
      "adjustment": [
        "재정은 무난하지만 작은 습관 차이가 결과를 크게 나눌 수 있습니다.",
        "반복 지출과 사소한 소비를 조정하는 것만으로도 체감이 달라질 수 있습니다.",
        "올해는 크게 벌이기보다 잘 새지 않게 관리하는 편이 좋습니다.",
        "돈 문제는 대담한 승부보다 생활 감각이 더 중요하게 작용할 수 있습니다."
      ],
      "harvest": [
        "크게 튀지는 않아도 관리해온 것이 안정감으로 돌아올 가능성이 있습니다.",
        "작은 절약과 정리가 차곡차곡 쌓여 체감으로 보일 수 있습니다.",
        "올해는 재정이 눈에 띄게 좋아지기보다 덜 흔들리는 방향으로 갈 가능성이 큽니다.",
        "무난한 흐름일수록 기본 관리를 잘한 사람이 편안함을 느낄 수 있습니다."
      ]
    },
    "work": {
      "foundation": [
        "일운은 기본기와 꾸준한 운영이 가장 중요하게 작용할 수 있습니다.",
        "새로운 판을 크게 벌이기보다 현재 역할을 안정적으로 수행하는 편이 더 좋을 수 있습니다.",
        "무난한 해일수록 실수 없는 처리와 꾸준함이 신뢰로 이어질 가능성이 큽니다.",
        "기록, 정리, 마감 태도 같은 기본기가 차이를 만들 수 있습니다."
      ],
      "adjustment": [
        "업무는 크게 흔들기보다 순서와 방식만 조금씩 조정하는 편이 현실적일 수 있습니다.",
        "작은 피로, 작은 혼선이 쌓이지 않도록 중간 점검을 자주 하는 편이 좋습니다.",
        "속도보다 안정적 운영이 더 잘 맞을 가능성이 있습니다.",
        "일이 크게 꼬이진 않아도 관리 소홀은 번거로움으로 이어질 수 있습니다."
      ],
      "harvest": [
        "일운은 조용한 누적이 결과로 이어질 가능성이 있습니다.",
        "눈에 띄는 성과보다 착실하게 쌓인 신뢰가 힘이 될 수 있습니다.",
        "기존에 해오던 일이 조금씩 가시화되거나 평가로 이어질 수 있습니다.",
        "무난한 흐름 안에서 작은 완성도를 잘 챙기는 사람이 유리할 수 있습니다."
      ]
    },
    "relationship": {
      "foundation": [
        "대인운은 넓히기보다 안정적으로 유지하는 쪽이 더 잘 맞을 수 있습니다.",
        "특별한 기복보다 기본적인 예의와 일관성이 더 중요할 가능성이 있습니다.",
        "무난한 흐름일수록 작은 배려와 꾸준한 반응이 관계를 오래 가게 만들 수 있습니다.",
        "좋은 사람을 많이 만드는 것보다 불편한 관계를 만들지 않는 것이 더 중요할 수 있습니다."
      ],
      "adjustment": [
        "관계는 크게 흔들기보다 작은 거리감 조정과 표현 방식 점검이 잘 맞을 수 있습니다.",
        "사람 사이의 피로를 줄이는 쪽으로 운영하면 훨씬 편안해질 가능성이 있습니다.",
        "무리하게 가까워지려 하기보다 자연스럽게 이어가는 편이 좋습니다.",
        "올해는 편안함과 선명함 사이의 균형을 찾는 것이 중요할 수 있습니다."
      ],
      "harvest": [
        "대인운은 조용하지만 안정적인 결과를 보여줄 가능성이 있습니다.",
        "남을 관계와 멀어질 관계가 자연스럽게 구분되면서 마음이 편해질 수 있습니다.",
        "크게 드러나지 않아도 믿을 수 있는 사람과의 연결이 더 단단해질 수 있습니다.",
        "무난한 흐름 안에서 관계의 질이 조금씩 좋아질 가능성이 있습니다."
      ]
    },
    "advice": {
      "foundation": [
        "올해는 기본을 지키는 태도가 가장 큰 힘이 될 수 있습니다.",
        "무리하게 흔들기보다 잘 유지하는 편이 더 좋은 결과로 이어질 수 있습니다.",
        "작은 관리 차이가 큰 체감 차이를 만들 수 있습니다.",
        "무난한 해일수록 기준과 루틴을 지키는 사람이 더 편하게 갈 수 있습니다."
      ]
    }
  }
}